werk24/__init__.py
werk24/_version.py
werk24/techread.py
werk24/cli/werk24.py
werk24/cli/commands/__init__.py
werk24/cli/commands/health_check.py
werk24/cli/commands/init.py
werk24/cli/commands/status.py
werk24/cli/commands/techread.py
werk24/cli/commands/version.py
werk24/models/__init__.py
werk24/models/v1/__init__.py
werk24/models/v1/alignment.py
werk24/models/v1/alphabet.py
werk24/models/v1/angle.py
werk24/models/v1/ask.py
werk24/models/v1/balloon.py
werk24/models/v1/base_feature.py
werk24/models/v1/bend.py
werk24/models/v1/bom_table.py
werk24/models/v1/chamfer.py
werk24/models/v1/complexity.py
werk24/models/v1/date.py
werk24/models/v1/depth.py
werk24/models/v1/file_format.py
werk24/models/v1/font.py
werk24/models/v1/fraction.py
werk24/models/v1/gdt.py
werk24/models/v1/gender.py
werk24/models/v1/general_tolerances.py
werk24/models/v1/geometric_shape.py
werk24/models/v1/helpdesk.py
werk24/models/v1/hole_feature.py
werk24/models/v1/icon.py
werk24/models/v1/insert.py
werk24/models/v1/language.py
werk24/models/v1/leader.py
werk24/models/v1/location.py
werk24/models/v1/material.py
werk24/models/v1/measure.py
werk24/models/v1/note.py
werk24/models/v1/paper_size.py
werk24/models/v1/part_family.py
werk24/models/v1/position.py
werk24/models/v1/process.py
werk24/models/v1/projection_method.py
werk24/models/v1/radius.py
werk24/models/v1/revision_table.py
werk24/models/v1/roughness.py
werk24/models/v1/shape.py
werk24/models/v1/size.py
werk24/models/v1/standard.py
werk24/models/v1/techread.py
werk24/models/v1/test_dimension.py
werk24/models/v1/thread.py
werk24/models/v1/thread_element.py
werk24/models/v1/title_block.py
werk24/models/v1/tolerance.py
werk24/models/v1/typed_model.py
werk24/models/v1/unit.py
werk24/models/v1/value.py
werk24/models/v1/view.py
werk24/models/v1/weight.py
werk24/models/v1/feature/__init__.py
werk24/models/v1/feature/base.py
werk24/models/v1/feature/chamfer.py
werk24/models/v1/feature/knurl.py
werk24/models/v1/property/__init__.py
werk24-2.3.0.dist-info/licenses/LICENSE.txt
werk24-2.3.0.dist-info/METADATA
werk24-2.3.0.dist-info/WHEEL
werk24-2.3.0.dist-info/entry_points.txt
werk24-2.3.0.dist-info/top_level.txt
werk24-2.3.0.dist-info/RECORD
