Metadata-Version: 2.4
Name: werk24
Version: 2.3.0
Summary: AI-powered platform for extracting and analyzing data from technical drawings / CAD drawings to enhance manufacturing workflows.
Author-email: W24 Service GmbH <info@werk24.io>
License: 
Project-URL: homepage, https://werk24.io
Project-URL: repository, https://github.com/W24-Service-GmbH/werk24-python
Project-URL: documentation, https://werk24.io/docs
Project-URL: changelog, https://github.com/W24-Service-GmbH/werk24-python/releases
Keywords: technical-drawings,CAD,AI,additive-manufacturing,feasibility,PMI,sheet-rebranding,title-block,tolerance,thread,chamfer,GDT,surface-roughness,API,feature-extraction,digitization,manufacturing,computer-vision,supply-chain,automation
Classifier: Development Status :: 5 - Production/Stable
Classifier: Intended Audience :: Developers
Classifier: Intended Audience :: Information Technology
Classifier: Operating System :: OS Independent
Classifier: Programming Language :: Python
Classifier: Programming Language :: Python :: 3
Classifier: Programming Language :: Python :: 3.10
Classifier: Programming Language :: Python :: 3.11
Classifier: Programming Language :: Python :: 3.12
Classifier: Programming Language :: Python :: 3.13
Classifier: Programming Language :: Python :: Implementation :: CPython
Classifier: Programming Language :: Python :: Implementation :: PyPy
Classifier: Topic :: Software Development
Classifier: Topic :: Software Development :: Libraries
Classifier: Topic :: Software Development :: Libraries :: Python Modules
Classifier: Topic :: Internet
Classifier: Topic :: Internet :: WWW/HTTP
Classifier: Topic :: Internet :: WWW/HTTP :: Dynamic Content
Classifier: Typing :: Typed
Classifier: Natural Language :: English
Classifier: Topic :: Scientific/Engineering :: Artificial Intelligence
Classifier: Topic :: Scientific/Engineering :: Information Analysis
Requires-Python: >=3.10
License-File: LICENSE.txt
Requires-Dist: aiohttp<=4.0.0,>=3.10.11
Requires-Dist: certifi>=2024.12.14
Requires-Dist: cryptography<=46.0.0,>=44.0.0
Requires-Dist: packaging<=25.0,>=24.2
Requires-Dist: pint<=0.25,>=0.24
Requires-Dist: pydantic-extra-types<=3.0.0,>=2.0.0
Requires-Dist: pydantic<=3.0.0,>=2.0.0
Requires-Dist: pydantic-settings<=3.0.0,>=2.0.0
Requires-Dist: python-dotenv<=2.0.0,>=1.0.0
Requires-Dist: typer<=0.16.0,>=0.15.0
Requires-Dist: websockets<15.0,>=14.2
Dynamic: license-file
